[
    {
        "componentChunkName": "component---src-pages-index-js",
        "jsonName": "index",
        "path": "/"
    },
    {
        "componentChunkName": "component---src-templates-single-js",
        "jsonName": "1899-1902-boer-war-680",
        "path": "/1899-1902-boer-war"
    },
    {
        "componentChunkName": "component---src-templates-single-js",
        "jsonName": "1939-australia-is-at-war-e42",
        "path": "/1939-australia-is-at-war"
    },
    {
        "componentChunkName": "component---src-templates-single-js",
        "jsonName": "1945-49-bcof-british-commonwealth-occupation-force-japan-c77",
        "path": "/1945-49-bcof-british-commonwealth-occupation-force-japan"
    },
    {
        "componentChunkName": "component---src-templates-single-js",
        "jsonName": "1947-2006-peacekeeping-general-f72",
        "path": "/1947-2006-peacekeeping-general"
    },
    {
        "componentChunkName": "component---src-templates-single-js",
        "jsonName": "1950-1953-korea-e89",
        "path": "/1950-1953-korea"
    },
    {
        "componentChunkName": "component---src-templates-single-js",
        "jsonName": "1950-1960-malayan-emergency-5a1",
        "path": "/1950-1960-malayan-emergency"
    },
    {
        "componentChunkName": "component---src-templates-single-js",
        "jsonName": "1962-1972-vietnam-e68",
        "path": "/1962-1972-vietnam"
    },
    {
        "componentChunkName": "component---src-templates-single-js",
        "jsonName": "1964-1966-indonesia-dbd",
        "path": "/1964-1966-indonesia"
    },
    {
        "componentChunkName": "component---src-templates-single-js",
        "jsonName": "1990-1991-gulf-16e",
        "path": "/1990-1991-gulf"
    },
    {
        "componentChunkName": "component---src-templates-single-js",
        "jsonName": "1999-2000-peacekeeping-east-timor-c41",
        "path": "/1999-2000-peacekeeping-east-timor"
    },
    {
        "componentChunkName": "component---src-templates-single-js",
        "jsonName": "2003-2006-iraq-2003-555",
        "path": "/2003-2006-iraq-2003"
    },
    {
        "componentChunkName": "component---src-templates-single-js",
        "jsonName": "2-nd-lieutenant-frederick-birks-f1b",
        "path": "/2nd-lieutenant-frederick-birks"
    },
    {
        "componentChunkName": "component---src-pages-404-js",
        "jsonName": "404-html-516",
        "path": "/404.html"
    },
    {
        "componentChunkName": "component---src-pages-404-js",
        "jsonName": "404-22d",
        "path": "/404/"
    },
    {
        "componentChunkName": "component---src-templates-article-js",
        "jsonName": "7-news-anzac-day-commemoration-committee-2dd",
        "path": "/7news-anzac-day-commemoration-committee"
    },
    {
        "componentChunkName": "component---src-templates-single-js",
        "jsonName": "a-brown-slouch-hat-cbc",
        "path": "/a-brown-slouch-hat"
    },
    {
        "componentChunkName": "component---src-templates-single-js",
        "jsonName": "a-case-study-4885-r-h-simpson-a83",
        "path": "/a-case-study-4885-r-h-simpson"
    },
    {
        "componentChunkName": "component---src-templates-single-js",
        "jsonName": "a-female-soldiers-viewpoint-5d0",
        "path": "/a-female-soldiers-viewpoint"
    },
    {
        "componentChunkName": "component---src-templates-single-js",
        "jsonName": "a-is-for-anzacs-ef9",
        "path": "/a-is-for-anzacs"
    },
    {
        "componentChunkName": "component---src-templates-single-js",
        "jsonName": "a-is-for-anzacs-1-d51",
        "path": "/a-is-for-anzacs-1"
    },
    {
        "componentChunkName": "component---src-templates-single-js",
        "jsonName": "a-land-fit-for-heroes-afd",
        "path": "/a-land-fit-for-heroes"
    },
    {
        "componentChunkName": "component---src-templates-single-js",
        "jsonName": "a-poem-for-remembrance-day-f8b",
        "path": "/a-poem-for-remembrance-day"
    },
    {
        "componentChunkName": "component---src-templates-single-js",
        "jsonName": "a-the-task-a8f",
        "path": "/a-the-task"
    },
    {
        "componentChunkName": "component---src-templates-single-js",
        "jsonName": "a-tribute-to-anzac-day-b1a",
        "path": "/a-tribute-to-anzac-day"
    },
    {
        "componentChunkName": "component---src-templates-single-js",
        "jsonName": "about-matt-anderson-9f4",
        "path": "/about-matt-anderson"
    },
    {
        "componentChunkName": "component---src-templates-single-js",
        "jsonName": "about-tom-curran-author-of-not-only-a-hero-a61",
        "path": "/about-tom-curran-author-of-not-only-a-hero"
    },
    {
        "componentChunkName": "component---src-templates-single-js",
        "jsonName": "about-us-a1f",
        "path": "/about-us"
    },
    {
        "componentChunkName": "component---src-templates-single-js",
        "jsonName": "acting-wing-commander-hughie-idwal-edwards-fe6",
        "path": "/acting-wing-commander-hughie-idwal-edwards"
    },
    {
        "componentChunkName": "component---src-templates-single-js",
        "jsonName": "activities-181",
        "path": "/activities"
    },
    {
        "componentChunkName": "component---src-templates-article-js",
        "jsonName": "adcc-100-year-celebration-a6a",
        "path": "/adcc-100-year-celebration"
    },
    {
        "componentChunkName": "component---src-templates-single-js",
        "jsonName": "adcc-merchandise-for-schools-88a",
        "path": "/adcc-merchandise-for-schools"
    },
    {
        "componentChunkName": "component---src-templates-single-js",
        "jsonName": "after-the-service-35c",
        "path": "/after-the-service"
    },
    {
        "componentChunkName": "component---src-templates-single-js",
        "jsonName": "albert-jacka-90c",
        "path": "/albert-jacka"
    },
    {
        "componentChunkName": "component---src-templates-single-js",
        "jsonName": "all-medals-and-awards-967",
        "path": "/all-medals-and-awards"
    },
    {
        "componentChunkName": "component---src-templates-single-js",
        "jsonName": "an-introduction-to-anzac-day-for-early-childhood-451",
        "path": "/an-introduction-to-anzac-day-for-early-childhood"
    },
    {
        "componentChunkName": "component---src-templates-single-js",
        "jsonName": "annual-anzac-day-ceremonies-132",
        "path": "/annual-anzac-day-ceremonies"
    },
    {
        "componentChunkName": "component---src-templates-single-js",
        "jsonName": "anzac-cove-3d7",
        "path": "/anzac-cove"
    },
    {
        "componentChunkName": "component---src-templates-single-js",
        "jsonName": "anzac-day-3ea",
        "path": "/anzac-day"
    },
    {
        "componentChunkName": "component---src-templates-single-js",
        "jsonName": "anzac-day-1-bb4",
        "path": "/anzac-day-1"
    },
    {
        "componentChunkName": "component---src-templates-single-js",
        "jsonName": "anzac-day-commemoration-bb3",
        "path": "/anzac-day-commemoration"
    },
    {
        "componentChunkName": "component---src-templates-single-js",
        "jsonName": "anzac-day-what-does-it-mean-to-you-today-120",
        "path": "/anzac-day-what-does-it-mean-to-you-today"
    },
    {
        "componentChunkName": "component---src-templates-single-js",
        "jsonName": "anzac-memorial-sydney-f80",
        "path": "/anzac-memorial-sydney"
    },
    {
        "componentChunkName": "component---src-pages-anzac-news-js",
        "jsonName": "anzac-news-cd0",
        "path": "/anzac-news/"
    },
    {
        "componentChunkName": "component---src-templates-single-js",
        "jsonName": "anzac-puzzles-ff9",
        "path": "/anzac-puzzles"
    },
    {
        "componentChunkName": "component---src-templates-single-js",
        "jsonName": "anzac-quiz-2be",
        "path": "/anzac-quiz"
    },
    {
        "componentChunkName": "component---src-templates-single-js",
        "jsonName": "anzac-requiem-0c2",
        "path": "/anzac-requiem"
    },
    {
        "componentChunkName": "component---src-templates-single-js",
        "jsonName": "army-issue-61a",
        "path": "/army-issue"
    },
    {
        "componentChunkName": "component---src-templates-single-js",
        "jsonName": "as-of-september-2005-40e",
        "path": "/as-of-september-2005"
    },
    {
        "componentChunkName": "component---src-templates-single-js",
        "jsonName": "australia-and-the-vietnam-war-why-did-australia-enter-the-war-in-1965-did-australians-support-this-decision-589",
        "path": "/australia-and-the-vietnam-war-why-did-australia-enter-the-war-in-1965-did-australians-support-this-decision"
    },
    {
        "componentChunkName": "component---src-templates-single-js",
        "jsonName": "australia-and-timor-ww-2-1e6",
        "path": "/australia-and-timor-ww2"
    },
    {
        "componentChunkName": "component---src-templates-single-js",
        "jsonName": "australian-light-horse-memorials-8ce",
        "path": "/australian-light-horse-memorials"
    },
    {
        "componentChunkName": "component---src-templates-single-js",
        "jsonName": "australian-war-memorial-london-8c9",
        "path": "/australian-war-memorial-london"
    },
    {
        "componentChunkName": "component---src-templates-single-js",
        "jsonName": "australian-war-memorials-414",
        "path": "/australian-war-memorials"
    },
    {
        "componentChunkName": "component---src-templates-single-js",
        "jsonName": "australian-ww-1-hospitals-bf5",
        "path": "/australian-ww1-hospitals"
    },
    {
        "componentChunkName": "component---src-templates-single-js",
        "jsonName": "australians-in-east-timor-98e",
        "path": "/australians-in-east-timor"
    },
    {
        "componentChunkName": "component---src-templates-single-js",
        "jsonName": "australias-war-dead-b21",
        "path": "/australia’s-war-dead"
    },
    {
        "componentChunkName": "component---src-templates-user-js",
        "jsonName": "authors-5-bd-2809-fc-4-e-12-e-00166-b-2208-8a6",
        "path": "/authors/5bd2809fc4e12e00166b2208"
    },
    {
        "componentChunkName": "component---src-templates-user-js",
        "jsonName": "authors-5-bd-7-f-76-fe-027-f-20016-ca-7-bb-0-918",
        "path": "/authors/5bd7f76fe027f20016ca7bb0"
    },
    {
        "componentChunkName": "component---src-templates-single-js",
        "jsonName": "awm-images-83f",
        "path": "/awm-images"
    },
    {
        "componentChunkName": "component---src-templates-single-js",
        "jsonName": "b-is-for-bully-beef-437",
        "path": "/b-is-for-bully-beef"
    },
    {
        "componentChunkName": "component---src-templates-single-js",
        "jsonName": "b-map-of-the-area-73f",
        "path": "/b-map-of-the-area"
    },
    {
        "componentChunkName": "component---src-templates-single-js",
        "jsonName": "bangka-island-971",
        "path": "/bangka-island"
    },
    {
        "componentChunkName": "component---src-templates-single-js",
        "jsonName": "battle-casualties-e47",
        "path": "/battle-casualties"
    },
    {
        "componentChunkName": "component---src-templates-single-js",
        "jsonName": "battle-of-kapyong-331",
        "path": "/battle-of-kapyong"
    },
    {
        "componentChunkName": "component---src-templates-single-js",
        "jsonName": "bcof-overview-f95",
        "path": "/bcof-overview"
    },
    {
        "componentChunkName": "component---src-templates-single-js",
        "jsonName": "bcof-supplementary-information-and-anecdotes-908",
        "path": "/bcof-supplementary-information-and-anecdotes"
    },
    {
        "componentChunkName": "component---src-templates-single-js",
        "jsonName": "being-a-historian-cc1",
        "path": "/being-a-historian"
    },
    {
        "componentChunkName": "component---src-templates-single-js",
        "jsonName": "bitter-medicine-1-11b",
        "path": "/bitter-medicine1"
    },
    {
        "componentChunkName": "component---src-templates-single-js",
        "jsonName": "book-support-page-for-in-search-of-ethel-allchin-955",
        "path": "/book-support-page-for-in-search-of-ethel-allchin"
    },
    {
        "componentChunkName": "component---src-templates-single-js",
        "jsonName": "book-support-page-for-in-search-of-jacka-vc-78c",
        "path": "/book-support-page-for-in-search-of-jacka-vc"
    },
    {
        "componentChunkName": "component---src-templates-single-js",
        "jsonName": "book-support-page-for-in-search-of-kingsford-smith-mc-d53",
        "path": "/book-support-page-for-in-search-of-kingsford-smith-mc"
    },
    {
        "componentChunkName": "component---src-templates-single-js",
        "jsonName": "book-support-page-for-in-search-of-series-b6d",
        "path": "/book-support-page-for-in-search-of-series"
    },
    {
        "componentChunkName": "component---src-templates-single-js",
        "jsonName": "book-support-page-for-in-search-of-sloan-bolton-dcm-9e1",
        "path": "/book-support-page-for-in-search-of-sloan-bolton-dcm"
    },
    {
        "componentChunkName": "component---src-templates-single-js",
        "jsonName": "book-support-page-for-in-search-of-the-ae-2-93a",
        "path": "/book-support-page-for-in-search-of-the-ae2"
    },
    {
        "componentChunkName": "component---src-templates-single-js",
        "jsonName": "books-posters-and-cd-rom-for-sale-869",
        "path": "/books-posters-and-cd-rom-for-sale"
    },
    {
        "componentChunkName": "component---src-templates-single-js",
        "jsonName": "books-posters-and-cd-roms-for-sale-866",
        "path": "/books-posters-and-cd-roms-for-sale"
    },
    {
        "componentChunkName": "component---src-templates-single-js",
        "jsonName": "british-commonwealth-occupation-force-cc0",
        "path": "/british-commonwealth-occupation-force"
    },
    {
        "componentChunkName": "component---src-templates-single-js",
        "jsonName": "bugle-calls-1d4",
        "path": "/bugle-calls"
    },
    {
        "componentChunkName": "component---src-templates-single-js",
        "jsonName": "c-advice-from-our-australian-expert-on-indonesia-f5a",
        "path": "/c-advice-from-our-australian-expert-on-indonesia"
    },
    {
        "componentChunkName": "component---src-templates-single-js",
        "jsonName": "c-is-for-colour-patches-a90",
        "path": "/c-is-for-colour-patches"
    },
    {
        "componentChunkName": "component---src-templates-single-js",
        "jsonName": "captain-alfred-john-shout-927",
        "path": "/captain-alfred-john-shout"
    },
    {
        "componentChunkName": "component---src-templates-single-js",
        "jsonName": "captain-clarence-smith-jeffries-d6f",
        "path": "/captain-clarence-smith-jeffries"
    },
    {
        "componentChunkName": "component---src-templates-single-js",
        "jsonName": "captain-frederick-harold-tubb-f75",
        "path": "/captain-frederick-harold-tubb"
    },
    {
        "componentChunkName": "component---src-templates-single-js",
        "jsonName": "captain-henry-william-murray-651",
        "path": "/captain-henry-william-murray"
    },
    {
        "componentChunkName": "component---src-templates-single-js",
        "jsonName": "captain-james-ernest-newland-1ae",
        "path": "/captain-james-ernest-newland"
    },
    {
        "componentChunkName": "component---src-templates-single-js",
        "jsonName": "captain-neville-reginald-howse-bcd",
        "path": "/captain-neville-reginald-howse"
    },
    {
        "componentChunkName": "component---src-templates-single-js",
        "jsonName": "captain-percy-herbert-cherry-632",
        "path": "/captain-percy-herbert-cherry"
    },
    {
        "componentChunkName": "component---src-templates-single-js",
        "jsonName": "captain-robert-cuthbert-grieve-462",
        "path": "/captain-robert-cuthbert-grieve"
    },
    {
        "componentChunkName": "component---src-templates-single-js",
        "jsonName": "case-study-of-a-world-war-1-service-record-383",
        "path": "/case-study-of-a-world-war-1-service-record"
    },
    {
        "componentChunkName": "component---src-templates-single-js",
        "jsonName": "charge-at-beersheba-f36",
        "path": "/charge-at-beersheba"
    },
    {
        "componentChunkName": "component---src-templates-single-js",
        "jsonName": "checking-your-gear-3a7",
        "path": "/checking-your-gear"
    },
    {
        "componentChunkName": "component---src-templates-single-js",
        "jsonName": "citation-for-the-victoria-cross-pte-ted-kenna-47d",
        "path": "/citation-for-the-victoria-cross-pte-ted-kenna"
    },
    {
        "componentChunkName": "component---src-templates-single-js",
        "jsonName": "classroom-activities-9f7",
        "path": "/classroom-activities"
    },
    {
        "componentChunkName": "component---src-templates-single-js",
        "jsonName": "colours-tell-the-story-c7a",
        "path": "/colours-tell-the-story"
    },
    {
        "componentChunkName": "component---src-templates-single-js",
        "jsonName": "commemoration-fc4",
        "path": "/commemoration"
    },
    {
        "componentChunkName": "component---src-templates-single-js",
        "jsonName": "commemoration-activities-7bd",
        "path": "/commemoration-activities"
    },
    {
        "componentChunkName": "component---src-templates-single-js",
        "jsonName": "commemoration-service-for-anzac-day-9cb",
        "path": "/commemoration-service-for-anzac-day"
    },
    {
        "componentChunkName": "component---src-templates-single-js",
        "jsonName": "community-742",
        "path": "/community"
    },
    {
        "componentChunkName": "component---src-templates-single-js",
        "jsonName": "confrontaion-australian-involvement-and-australian-casualties-981",
        "path": "/confrontaion-australian-involvement-and-australian-casualties"
    },
    {
        "componentChunkName": "component---src-templates-single-js",
        "jsonName": "confrontation-supplementary-information-and-anecdotes-d4f",
        "path": "/confrontation-supplementary-information-and-anecdotes"
    },
    {
        "componentChunkName": "component---src-templates-single-js",
        "jsonName": "confrontation-with-indonesia-1962-1966-29a",
        "path": "/confrontation-with-indonesia-1962-1966"
    },
    {
        "componentChunkName": "component---src-templates-single-js",
        "jsonName": "confrontation-with-indonesia-1964-66-would-you-be-a-good-foreign-affairs-decision-maker-0bb",
        "path": "/confrontation-with-indonesia-1964-66-would-you-be-a-good-foreign-affairs-decision-maker"
    },
    {
        "componentChunkName": "component---src-templates-single-js",
        "jsonName": "confrontation-with-indonesia-overview-2f1",
        "path": "/confrontation-with-indonesia-overview"
    },
    {
        "componentChunkName": "component---src-templates-single-js",
        "jsonName": "controls-37f",
        "path": "/controls"
    },
    {
        "componentChunkName": "component---src-templates-single-js",
        "jsonName": "corporal-alexander-stewart-burton-93e",
        "path": "/corporal-alexander-stewart-burton"
    },
    {
        "componentChunkName": "component---src-templates-single-js",
        "jsonName": "corporal-arthur-charles-hall-7ac",
        "path": "/corporal-arthur-charles-hall"
    },
    {
        "componentChunkName": "component---src-templates-single-js",
        "jsonName": "corporal-arthur-percy-sullivan-4f5",
        "path": "/corporal-arthur-percy-sullivan"
    },
    {
        "componentChunkName": "component---src-templates-single-js",
        "jsonName": "corporal-george-julian-howell-1c3",
        "path": "/corporal-george-julian-howell"
    },
    {
        "componentChunkName": "component---src-templates-single-js",
        "jsonName": "corporal-john-alexander-french-d79",
        "path": "/corporal-john-alexander-french"
    },
    {
        "componentChunkName": "component---src-templates-single-js",
        "jsonName": "corporal-john-bernard-mackey-533",
        "path": "/corporal-john-bernard-mackey"
    },
    {
        "componentChunkName": "component---src-templates-single-js",
        "jsonName": "corporal-john-hurst-edmondson-fcc",
        "path": "/corporal-john-hurst-edmondson"
    },
    {
        "componentChunkName": "component---src-templates-single-js",
        "jsonName": "corporal-phillip-davey-7f3",
        "path": "/corporal-phillip-davey"
    },
    {
        "componentChunkName": "component---src-templates-single-js",
        "jsonName": "corporal-reginald-roy-rattey-ce5",
        "path": "/corporal-reginald-roy-rattey"
    },
    {
        "componentChunkName": "component---src-templates-single-js",
        "jsonName": "corporal-walter-ernest-brown-c99",
        "path": "/corporal-walter-ernest-brown"
    },
    {
        "componentChunkName": "component---src-templates-single-js",
        "jsonName": "corporal-william-dunstan-f29",
        "path": "/corporal-william-dunstan"
    },
    {
        "componentChunkName": "component---src-templates-single-js",
        "jsonName": "cowra-62a",
        "path": "/cowra"
    },
    {
        "componentChunkName": "component---src-templates-single-js",
        "jsonName": "current-catalogue-937",
        "path": "/current-catalogue"
    },
    {
        "componentChunkName": "component---src-templates-single-js",
        "jsonName": "d-advice-from-our-australian-expert-on-great-britain-f88",
        "path": "/d-advice-from-our-australian-expert-on-great-britain"
    },
    {
        "componentChunkName": "component---src-templates-single-js",
        "jsonName": "d-day-25-years-on-the-battle-of-binh-ba-26a",
        "path": "/d-day-25-years-on-the-battle-of-binh-ba"
    },
    {
        "componentChunkName": "component---src-templates-single-js",
        "jsonName": "d-is-for-digger-819",
        "path": "/d-is-for-digger"
    },
    {
        "componentChunkName": "component---src-templates-single-js",
        "jsonName": "darwin-cenotaph-13c",
        "path": "/darwin-cenotaph"
    },
    {
        "componentChunkName": "component---src-templates-single-js",
        "jsonName": "death-of-ralph-niblett-889",
        "path": "/death-of-ralph-niblett"
    },
    {
        "componentChunkName": "component---src-templates-single-js",
        "jsonName": "deathrailway-4f7",
        "path": "/deathrailway"
    },
    {
        "componentChunkName": "component---cache-dev-404-page-js",
        "jsonName": "dev-404-page-5f9",
        "path": "/dev-404-page/"
    },
    {
        "componentChunkName": "component---src-templates-single-js",
        "jsonName": "did-australians-oppose-conscription-4ff",
        "path": "/did-australians-oppose-conscription"
    },
    {
        "componentChunkName": "component---src-templates-single-js",
        "jsonName": "did-australians-strongly-oppose-involvement-in-the-vietnam-war-bbe",
        "path": "/did-australians-strongly-oppose-involvement-in-the-vietnam-war"
    },
    {
        "componentChunkName": "component---src-templates-single-js",
        "jsonName": "did-the-election-of-prime-minister-whitlam-in-december-1972-lead-to-australian-troops-being-returned-from-vietnam-ba5",
        "path": "/did-the-election-of-prime-minister-whitlam-in-december-1972-lead-to-australian-troops-being-returned-from-vietnam"
    },
    {
        "componentChunkName": "component---src-templates-single-js",
        "jsonName": "did-you-serve-in-vietnam-cfd",
        "path": "/did-you-serve-in-vietnam"
    },
    {
        "componentChunkName": "component---src-templates-single-js",
        "jsonName": "digging-790",
        "path": "/digging"
    },
    {
        "componentChunkName": "component---src-templates-single-js",
        "jsonName": "discussion-points-a17",
        "path": "/discussion-points"
    },
    {
        "componentChunkName": "component---src-templates-single-js",
        "jsonName": "documents-supporting-the-activity-01d",
        "path": "/documents-supporting-the-activity"
    },
    {
        "componentChunkName": "component---src-templates-single-js",
        "jsonName": "download-tips-be1",
        "path": "/download-tips"
    },
    {
        "componentChunkName": "component---src-templates-single-js",
        "jsonName": "downloadable-forms-fbe",
        "path": "/downloadable-forms"
    },
    {
        "componentChunkName": "component---src-templates-single-js",
        "jsonName": "dusty-track-147",
        "path": "/dusty_track"
    },
    {
        "componentChunkName": "component---src-templates-single-js",
        "jsonName": "e-advice-from-our-australian-expert-on-united-states-of-america-b14",
        "path": "/e-advice-from-our-australian-expert-on-united-states-of-america"
    },
    {
        "componentChunkName": "component---src-templates-single-js",
        "jsonName": "e-is-for-enlistment-e7b",
        "path": "/e-is-for-enlistment"
    },
    {
        "componentChunkName": "component---src-templates-single-js",
        "jsonName": "east-timor-supplementary-information-and-anecdotes-4ba",
        "path": "/east-timor-supplementary-information-and-anecdotes"
    },
    {
        "componentChunkName": "component---src-templates-single-js",
        "jsonName": "east-timor-comment-from-major-general-peter-cosgrove-e00",
        "path": "/east_timor-comment-from-major-general-peter-cosgrove"
    },
    {
        "componentChunkName": "component---src-templates-single-js",
        "jsonName": "east-timor-overview-900",
        "path": "/east_timor-overview"
    },
    {
        "componentChunkName": "component---src-templates-single-js",
        "jsonName": "education-006",
        "path": "/education"
    },
    {
        "componentChunkName": "component---src-templates-single-js",
        "jsonName": "enemy-ef9",
        "path": "/enemy"
    },
    {
        "componentChunkName": "component---src-templates-single-js",
        "jsonName": "equality-6f5",
        "path": "/equality"
    },
    {
        "componentChunkName": "component---src-templates-single-js",
        "jsonName": "every-penny-counts-3bd",
        "path": "/every-penny-counts"
    },
    {
        "componentChunkName": "component---src-templates-single-js",
        "jsonName": "everyday-7e5",
        "path": "/everyday"
    },
    {
        "componentChunkName": "component---src-templates-single-js",
        "jsonName": "explanation-of-defence-force-ranks-219",
        "path": "/explanation-of-defence-force-ranks"
    },
    {
        "componentChunkName": "component---src-templates-single-js",
        "jsonName": "exploring-the-legend-and-reality-of-sir-charles-kingsford-smith-644",
        "path": "/exploring-the-legend-and-reality-of-sir-charles-kingsford-smith"
    },
    {
        "componentChunkName": "component---src-templates-single-js",
        "jsonName": "f-advice-from-our-australian-expert-on-malaysia-f1c",
        "path": "/f-advice-from-our-australian-expert-on-malaysia"
    },
    {
        "componentChunkName": "component---src-templates-single-js",
        "jsonName": "f-is-for-friendship-324",
        "path": "/f-is-for-friendship"
    },
    {
        "componentChunkName": "component---src-templates-single-js",
        "jsonName": "family-a86",
        "path": "/family"
    },
    {
        "componentChunkName": "component---src-templates-single-js",
        "jsonName": "finding-evidence-of-the-impact-of-war-on-your-community-138",
        "path": "/finding-evidence-of-the-impact-of-war-on-your-community"
    },
    {
        "componentChunkName": "component---src-templates-single-js",
        "jsonName": "finding-out-about-anzac-day-494",
        "path": "/finding-out-about-anzac-day"
    },
    {
        "componentChunkName": "component---src-templates-single-js",
        "jsonName": "finding-treasures-at-home-2ec",
        "path": "/finding-treasures-at-home"
    },
    {
        "componentChunkName": "component---src-templates-single-js",
        "jsonName": "flight-lieutenant-william-ellis-newton-7f2",
        "path": "/flight-lieutenant-william-ellis-newton"
    },
    {
        "componentChunkName": "component---src-templates-single-js",
        "jsonName": "flight-sergeant-rawdon-hume-middleton-945",
        "path": "/flight-sergeant-rawdon-hume-middleton"
    },
    {
        "componentChunkName": "component---src-templates-single-js",
        "jsonName": "flying-the-flag-9da",
        "path": "/flying-the-flag"
    },
    {
        "componentChunkName": "component---src-templates-single-js",
        "jsonName": "for-the-fallen-ae9",
        "path": "/for-the-fallen"
    },
    {
        "componentChunkName": "component---src-templates-single-js",
        "jsonName": "g-australias-requirements-and-priorities-7cf",
        "path": "/g-australias-requirements-and-priorities"
    },
    {
        "componentChunkName": "component---src-templates-single-js",
        "jsonName": "g-is-for-gallipoli-9e4",
        "path": "/g-is-for-gallipoli"
    },
    {
        "componentChunkName": "component---src-templates-single-js",
        "jsonName": "gaps-in-the-ranks-688",
        "path": "/gaps-in-the-ranks"
    },
    {
        "componentChunkName": "component---src-templates-single-js",
        "jsonName": "gassed-last-night-c2f",
        "path": "/gassed-last-night"
    },
    {
        "componentChunkName": "component---src-templates-single-js",
        "jsonName": "gateway-to-hell-247",
        "path": "/gateway-to-hell"
    },
    {
        "componentChunkName": "component---src-templates-single-js",
        "jsonName": "grandpa-what-did-you-do-in-the-war-68a",
        "path": "/grandpa-what-did-you-do-in-the-war"
    },
    {
        "componentChunkName": "component---src-templates-single-js",
        "jsonName": "gulf-war-7ef",
        "path": "/gulf_war"
    },
    {
        "componentChunkName": "component---src-templates-single-js",
        "jsonName": "h-is-for-home-front-e05",
        "path": "/h-is-for-home-front"
    },
    {
        "componentChunkName": "component---src-templates-single-js",
        "jsonName": "h-making-decisions-3d6",
        "path": "/h-making-decisions"
    },
    {
        "componentChunkName": "component---src-templates-single-js",
        "jsonName": "heroes-6ed",
        "path": "/heroes"
    },
    {
        "componentChunkName": "component---src-templates-single-js",
        "jsonName": "hints-for-conducting-a-successful-interview-694",
        "path": "/hints-for-conducting-a-successful-interview"
    },
    {
        "componentChunkName": "component---src-templates-single-js",
        "jsonName": "history-72c",
        "path": "/history"
    },
    {
        "componentChunkName": "component---src-templates-single-js",
        "jsonName": "hobart-war-memorial-cenotaph-7c6",
        "path": "/hobart-war-memorial-cenotaph"
    },
    {
        "componentChunkName": "component---src-templates-single-js",
        "jsonName": "homefront-during-world-war-2-59b",
        "path": "/homefront-during-world-war2"
    },
    {
        "componentChunkName": "component---src-templates-single-js",
        "jsonName": "hymns-d75",
        "path": "/hymns"
    },
    {
        "componentChunkName": "component---src-templates-single-js",
        "jsonName": "i-is-for-ice-a9b",
        "path": "/i-is-for-ice"
    },
    {
        "componentChunkName": "component---src-templates-single-js",
        "jsonName": "i-record-sheet-point-score-sheet-867",
        "path": "/i-record-sheet-point-score-sheet"
    },
    {
        "componentChunkName": "component---src-templates-single-js",
        "jsonName": "incident-off-chau-khe-north-vietnam-18-october-1967-eb9",
        "path": "/incident-off-chau-khe-north-vietnam-18-october-1967"
    },
    {
        "componentChunkName": "component---src-templates-single-js",
        "jsonName": "independence-201",
        "path": "/independence"
    },
    {
        "componentChunkName": "component---src-templates-single-js",
        "jsonName": "infantryman-2cd",
        "path": "/infantryman"
    },
    {
        "componentChunkName": "component---src-templates-single-js",
        "jsonName": "interactives-40a",
        "path": "/interactives"
    },
    {
        "componentChunkName": "component---src-templates-single-js",
        "jsonName": "into-battle-33c",
        "path": "/into-battle"
    },
    {
        "componentChunkName": "component---src-templates-single-js",
        "jsonName": "introduction-smithys-missing-978",
        "path": "/introduction-smithys-missing"
    },
    {
        "componentChunkName": "component---src-templates-single-js",
        "jsonName": "investigating-sources-what-happened-to-private-john-mcquat-0e3",
        "path": "/investigating-sources-what-happened-to-private-john-mcquat"
    },
    {
        "componentChunkName": "component---src-templates-single-js",
        "jsonName": "investigating-the-image-presented-61e",
        "path": "/investigating-the-image-presented"
    },
    {
        "componentChunkName": "component---src-templates-single-js",
        "jsonName": "investigating-the-impact-of-the-american-invasion-of-australia-1942-45-552",
        "path": "/investigating-the-impact-of-the-american-invasion-of-australia-1942-45"
    },
    {
        "componentChunkName": "component---src-templates-single-js",
        "jsonName": "investigating-the-reality-what-women-did-5ed",
        "path": "/investigating-the-reality-what-women-did"
    },
    {
        "componentChunkName": "component---src-templates-single-js",
        "jsonName": "investigating-the-reality-what-women-did-and-were-paid-131",
        "path": "/investigating-the-reality-what-women-did-and-were-paid"
    },
    {
        "componentChunkName": "component---src-templates-single-js",
        "jsonName": "investigating-the-reality-why-some-women-did-join-896",
        "path": "/investigating-the-reality-why-some-women-did-join"
    },
    {
        "componentChunkName": "component---src-templates-single-js",
        "jsonName": "investigating-the-reality-why-some-women-did-not-join-1f3",
        "path": "/investigating-the-reality-why-some-women-did-not-join"
    },
    {
        "componentChunkName": "component---src-templates-single-js",
        "jsonName": "investigating-the-spirit-of-anzac-image-and-reality-c12",
        "path": "/investigating-the-spirit-of-anzac-image-and-reality"
    },
    {
        "componentChunkName": "component---src-templates-single-js",
        "jsonName": "is-it-continuing-the-spirit-of-anzac-a6f",
        "path": "/is-it-continuing-the-spirit-of-anzac"
    },
    {
        "componentChunkName": "component---src-templates-single-js",
        "jsonName": "island-defenders-4e3",
        "path": "/island_defenders"
    },
    {
        "componentChunkName": "component---src-templates-single-js",
        "jsonName": "j-is-for-jacka-6e4",
        "path": "/j-is-for-jacka"
    },
    {
        "componentChunkName": "component---src-templates-single-js",
        "jsonName": "j-situation-decision-consequence-sheet-316",
        "path": "/j-situation-decision-consequence-sheet"
    },
    {
        "componentChunkName": "component---src-templates-single-js",
        "jsonName": "jack-in-australia-900",
        "path": "/jack-in-australia"
    },
    {
        "componentChunkName": "component---src-templates-single-js",
        "jsonName": "jumping-into-history-95c",
        "path": "/jumping-into-history"
    },
    {
        "componentChunkName": "component---src-templates-single-js",
        "jsonName": "just-soldiers-ece",
        "path": "/just-soldiers"
    },
    {
        "componentChunkName": "component---src-templates-single-js",
        "jsonName": "k-is-for-kit-ec4",
        "path": "/k-is-for-kit"
    },
    {
        "componentChunkName": "component---src-templates-single-js",
        "jsonName": "k-what-really-happened-22a",
        "path": "/k-what-really-happened"
    },
    {
        "componentChunkName": "component---src-templates-single-js",
        "jsonName": "kokoda-c40",
        "path": "/kokoda"
    },
    {
        "componentChunkName": "component---src-templates-single-js",
        "jsonName": "korea-australian-involvement-and-chronology-edb",
        "path": "/korea-australian-involvement-and-chronology"
    },
    {
        "componentChunkName": "component---src-templates-single-js",
        "jsonName": "korea-mrs-kims-story-7f1",
        "path": "/korea-mrs-kims-story"
    },
    {
        "componentChunkName": "component---src-templates-single-js",
        "jsonName": "korea-prisoners-of-war-f2e",
        "path": "/korea-prisoners-of-war"
    },
    {
        "componentChunkName": "component---src-templates-single-js",
        "jsonName": "korea-war-at-sea-210",
        "path": "/korea-war-at-sea"
    },
    {
        "componentChunkName": "component---src-templates-single-js",
        "jsonName": "korean-war-4a4",
        "path": "/korean-war"
    },
    {
        "componentChunkName": "component---src-templates-single-js",
        "jsonName": "korean-war-overview-of-the-conflict-629",
        "path": "/korean-war-overview-of-the-conflict"
    },
    {
        "componentChunkName": "component---src-templates-single-js",
        "jsonName": "korean-war-supplementary-information-and-anecdotes-fb3",
        "path": "/korean-war-supplementary-information-and-anecdotes"
    },
    {
        "componentChunkName": "component---src-templates-single-js",
        "jsonName": "l-is-for-letters-home-b25",
        "path": "/l-is-for-letters-home"
    },
    {
        "componentChunkName": "component---src-templates-single-js",
        "jsonName": "lance-corporal-albert-jacka-db5",
        "path": "/lance-corporal-albert-jacka"
    },
    {
        "componentChunkName": "component---src-templates-single-js",
        "jsonName": "lance-corporal-bernard-sidney-gordon-194",
        "path": "/lance-corporal-bernard-sidney-gordon"
    },
    {
        "componentChunkName": "component---src-templates-single-js",
        "jsonName": "lance-corporal-leonard-maurice-keysor-01b",
        "path": "/lance-corporal-leonard-maurice-keysor"
    },
    {
        "componentChunkName": "component---src-templates-single-js",
        "jsonName": "lance-corporal-thomas-leslie-axford-bbc",
        "path": "/lance-corporal-thomas-leslie-axford"
    },
    {
        "componentChunkName": "component---src-templates-single-js",
        "jsonName": "lance-corporal-walter-peeler-9ce",
        "path": "/lance-corporal-walter-peeler"
    },
    {
        "componentChunkName": "component---src-templates-single-js",
        "jsonName": "last-voyage-of-ae-2-36b",
        "path": "/last-voyage-of-ae2"
    },
    {
        "componentChunkName": "component---src-templates-single-js",
        "jsonName": "legacies-5a4",
        "path": "/legacies"
    },
    {
        "componentChunkName": "component---src-templates-single-js",
        "jsonName": "lieutenant-albert-chalmers-945",
        "path": "/lieutenant-albert-chalmers"
    },
    {
        "componentChunkName": "component---src-templates-single-js",
        "jsonName": "lieutenant-albert-chowne-cba",
        "path": "/lieutenant-albert-chowne"
    },
    {
        "componentChunkName": "component---src-templates-single-js",
        "jsonName": "lieutenant-alfred-edward-gaby-dbc",
        "path": "/lieutenant-alfred-edward-gaby"
    },
    {
        "componentChunkName": "component---src-templates-single-js",
        "jsonName": "lieutenant-arthur-roden-cutler-5ce",
        "path": "/lieutenant-arthur-roden-cutler"
    },
    {
        "componentChunkName": "component---src-templates-single-js",
        "jsonName": "lieutenant-arthur-seaforth-blackburn-e93",
        "path": "/lieutenant-arthur-seaforth-blackburn"
    },
    {
        "componentChunkName": "component---src-templates-single-js",
        "jsonName": "lieutenant-charles-pope-cc3",
        "path": "/lieutenant-charles-pope"
    },
    {
        "componentChunkName": "component---src-templates-single-js",
        "jsonName": "lieutenant-clifford-william-king-sadlier-033",
        "path": "/lieutenant-clifford-william-king-sadlier"
    },
    {
        "componentChunkName": "component---src-templates-single-js",
        "jsonName": "lieutenant-colonel-charles-groves-wright-anderson-168",
        "path": "/lieutenant-colonel-charles-groves-wright-anderson"
    },
    {
        "componentChunkName": "component---src-templates-single-js",
        "jsonName": "lieutenant-edgar-thomas-towner-96f",
        "path": "/lieutenant-edgar-thomas-towner"
    },
    {
        "componentChunkName": "component---src-templates-single-js",
        "jsonName": "lieutenant-frank-hubert-mcnamara-55f",
        "path": "/lieutenant-frank-hubert-mcnamara"
    },
    {
        "componentChunkName": "component---src-templates-single-js",
        "jsonName": "lieutenant-frederick-william-bell-099",
        "path": "/lieutenant-frederick-william-bell"
    },
    {
        "componentChunkName": "component---src-templates-single-js",
        "jsonName": "lieutenant-george-mawby-ingram-f35",
        "path": "/lieutenant-george-mawby-ingram"
    },
    {
        "componentChunkName": "component---src-templates-single-js",
        "jsonName": "lieutenant-guy-george-egerton-wylly-f18",
        "path": "/lieutenant-guy-george-egerton-wylly"
    },
    {
        "componentChunkName": "component---src-templates-single-js",
        "jsonName": "lieutenant-joseph-maxwell-0e6",
        "path": "/lieutenant-joseph-maxwell"
    },
    {
        "componentChunkName": "component---src-templates-single-js",
        "jsonName": "lieutenant-lawrence-laurence-dominic-mccarthy-373",
        "path": "/lieutenant-lawrence-laurence-dominic-mccarthy"
    },
    {
        "componentChunkName": "component---src-templates-single-js",
        "jsonName": "lieutenant-leslie-cecil-maygar-f5c",
        "path": "/lieutenant-leslie-cecil-maygar"
    },
    {
        "componentChunkName": "component---src-templates-single-js",
        "jsonName": "lieutenant-percy-valentine-storkey-e7e",
        "path": "/lieutenant-percy-valentine-storkey"
    },
    {
        "componentChunkName": "component---src-templates-single-js",
        "jsonName": "lieutenant-rupert-vance-moon-18d",
        "path": "/lieutenant-rupert-vance-moon"
    },
    {
        "componentChunkName": "component---src-templates-single-js",
        "jsonName": "lieutenant-william-donovan-joynt-d9f",
        "path": "/lieutenant-william-donovan-joynt"
    },
    {
        "componentChunkName": "component---src-templates-single-js",
        "jsonName": "lieutenant-william-john-symons-8c4",
        "path": "/lieutenant-william-john-symons"
    },
    {
        "componentChunkName": "component---src-templates-single-js",
        "jsonName": "list-of-australians-awarded-the-victoria-cross-1d2",
        "path": "/list-of-australians-awarded-the-victoria-cross"
    },
    {
        "componentChunkName": "component---src-pages-list-of-pages-js",
        "jsonName": "list-of-pages-7be",
        "path": "/list-of-pages/"
    },
    {
        "componentChunkName": "component---src-templates-single-js",
        "jsonName": "lone-pine-and-the-nek-2da",
        "path": "/lone-pine-and-the-nek"
    },
    {
        "componentChunkName": "component---src-templates-single-js",
        "jsonName": "longtan-d66",
        "path": "/longtan"
    },
    {
        "componentChunkName": "component---src-templates-single-js",
        "jsonName": "m-is-for-medals-a53",
        "path": "/m-is-for-medals"
    },
    {
        "componentChunkName": "component---src-templates-single-js",
        "jsonName": "major-blair-anderson-wark-735",
        "path": "/major-blair-anderson-wark"
    },
    {
        "componentChunkName": "component---src-templates-single-js",
        "jsonName": "major-peter-john-badcoe-0dd",
        "path": "/major-peter-john-badcoe"
    },
    {
        "componentChunkName": "component---src-templates-single-js",
        "jsonName": "malayan-emergency-c7a",
        "path": "/malayan-emergency"
    },
    {
        "componentChunkName": "component---src-templates-single-js",
        "jsonName": "malayan-emergency-australian-involvement-and-casualties-826",
        "path": "/malayan-emergency-australian-involvement-and-casualties"
    },
    {
        "componentChunkName": "component---src-templates-single-js",
        "jsonName": "malayan-emergency-overview-19c",
        "path": "/malayan-emergency-overview"
    },
    {
        "componentChunkName": "component---src-templates-single-js",
        "jsonName": "malayan-emergency-supplementary-information-and-anecdotes-060",
        "path": "/malayan-emergency-supplementary-information-and-anecdotes"
    },
    {
        "componentChunkName": "component---src-templates-single-js",
        "jsonName": "maps-923",
        "path": "/maps"
    },
    {
        "componentChunkName": "component---src-templates-single-js",
        "jsonName": "maps-of-conflicts-in-other-areas-8f6",
        "path": "/maps-of-conflicts-in-other-areas"
    },
    {
        "componentChunkName": "component---src-templates-single-js",
        "jsonName": "maps-of-world-war-1-a4c",
        "path": "/maps-of-world-war-1"
    },
    {
        "componentChunkName": "component---src-templates-single-js",
        "jsonName": "maps-of-world-war-2-8d6",
        "path": "/maps-of-world-war-2"
    },
    {
        "componentChunkName": "component---src-templates-single-js",
        "jsonName": "may-19-th-d69",
        "path": "/may-19th"
    },
    {
        "componentChunkName": "component---src-templates-single-js",
        "jsonName": "medallions-for-sale-568",
        "path": "/medallions-for-sale"
    },
    {
        "componentChunkName": "component---src-templates-single-js",
        "jsonName": "medals-604",
        "path": "/medals"
    },
    {
        "componentChunkName": "component---src-templates-single-js",
        "jsonName": "medals-awarded-for-active-service-or-peacekeeping-operations-836",
        "path": "/medals-awarded-for-active-service-or-peacekeeping-operations"
    },
    {
        "componentChunkName": "component---src-templates-single-js",
        "jsonName": "medals-awarded-for-long-service-or-non-operational-achievements-a7e",
        "path": "/medals-awarded-for-long-service-or-non-operational-achievements"
    },
    {
        "componentChunkName": "component---src-templates-single-js",
        "jsonName": "medals-korean-war-df8",
        "path": "/medals-korean-war"
    },
    {
        "componentChunkName": "component---src-templates-single-js",
        "jsonName": "medals-tff-6f0",
        "path": "/medals-tff"
    },
    {
        "componentChunkName": "component---src-templates-single-js",
        "jsonName": "medals-vietnam-war-f59",
        "path": "/medals-vietnam-war"
    },
    {
        "componentChunkName": "component---src-templates-single-js",
        "jsonName": "medals-which-are-not-campaign-specific-3c2",
        "path": "/medals-which-are-not-campaign-specific"
    },
    {
        "componentChunkName": "component---src-templates-single-js",
        "jsonName": "medals-world-war-1-bdf",
        "path": "/medals-world-war-1"
    },
    {
        "componentChunkName": "component---src-templates-single-js",
        "jsonName": "medals-world-war-2-b24",
        "path": "/medals-world-war-2"
    },
    {
        "componentChunkName": "component---src-templates-single-js",
        "jsonName": "memorials-2d3",
        "path": "/memorials"
    },
    {
        "componentChunkName": "component---src-templates-single-js",
        "jsonName": "memorials-in-anzac-parade-d16",
        "path": "/memorials-in-anzac-parade"
    },
    {
        "componentChunkName": "component---src-templates-single-js",
        "jsonName": "milnebay-cfa",
        "path": "/milnebay"
    },
    {
        "componentChunkName": "component---src-templates-single-js",
        "jsonName": "miscellaneous-3bd",
        "path": "/miscellaneous"
    },
    {
        "componentChunkName": "component---src-templates-single-js",
        "jsonName": "n-is-for-nurses-2a2",
        "path": "/n-is-for-nurses"
    },
    {
        "componentChunkName": "component---src-templates-single-js",
        "jsonName": "national-war-memorial-adelaide-335",
        "path": "/national-war-memorial-adelaide"
    },
    {
        "componentChunkName": "component---src-templates-single-js",
        "jsonName": "nine-rules-for-australian-army-forces-9cd",
        "path": "/nine-rules-for-australian-army-forces"
    },
    {
        "componentChunkName": "component---src-templates-single-js",
        "jsonName": "no-talking-lads-no-smoking-68c",
        "path": "/no-talking-lads-no-smoking"
    },
    {
        "componentChunkName": "component---src-templates-single-js",
        "jsonName": "not-a-hero-dee",
        "path": "/not-a-hero"
    },
    {
        "componentChunkName": "component---src-templates-single-js",
        "jsonName": "not-only-a-hero-680",
        "path": "/not-only-a-hero"
    },
    {
        "componentChunkName": "component---src-templates-single-js",
        "jsonName": "notes-56d",
        "path": "/notes"
    },
    {
        "componentChunkName": "component---src-templates-single-js",
        "jsonName": "o-is-for-observation-1c6",
        "path": "/o-is-for-observation"
    },
    {
        "componentChunkName": "component---src-templates-single-js",
        "jsonName": "on-patrol-with-b-company-3-rd-battalion-royal-australian-regiment-133",
        "path": "/on-patrol-with-b-company-3rd-battalion-royal-australian-regiment"
    },
    {
        "componentChunkName": "component---src-templates-single-js",
        "jsonName": "one-waaaf-remembers-9f3",
        "path": "/one-waaaf-remembers"
    },
    {
        "componentChunkName": "component---src-templates-single-js",
        "jsonName": "op-commando-e3f",
        "path": "/op_commando"
    },
    {
        "componentChunkName": "component---src-templates-single-js",
        "jsonName": "outcomes-and-investigations-3d9",
        "path": "/outcomes-and-investigations"
    },
    {
        "componentChunkName": "component---src-templates-single-js",
        "jsonName": "outline-commemoration-service-for-anzac-day-acf",
        "path": "/outline-commemoration-service-for-anzac-day"
    },
    {
        "componentChunkName": "component---src-templates-single-js",
        "jsonName": "overview-of-activity-aaa",
        "path": "/overview-of-activity"
    },
    {
        "componentChunkName": "component---src-templates-single-js",
        "jsonName": "p-is-for-poppy-dd0",
        "path": "/p-is-for-poppy"
    },
    {
        "componentChunkName": "component---src-templates-single-js",
        "jsonName": "paper-activities-making-an-anzac-day-wreath-966",
        "path": "/paper-activities-making-an-anzac-day-wreath"
    },
    {
        "componentChunkName": "component---src-templates-single-js",
        "jsonName": "part-1-australia-and-new-zealand-the-anzac-connection-130",
        "path": "/part-1-australia-and-new-zealand-the-anzac-connection"
    },
    {
        "componentChunkName": "component---src-templates-single-js",
        "jsonName": "part-2-war-d72",
        "path": "/part-2-war"
    },
    {
        "componentChunkName": "component---src-templates-single-js",
        "jsonName": "part-3-defence-forces-88f",
        "path": "/part-3-defence-forces"
    },
    {
        "componentChunkName": "component---src-templates-single-js",
        "jsonName": "part-4-anzac-day-c50",
        "path": "/part-4-anzac-day"
    },
    {
        "componentChunkName": "component---src-templates-single-js",
        "jsonName": "peace-keeping-944",
        "path": "/peace-keeping"
    },
    {
        "componentChunkName": "component---src-templates-single-js",
        "jsonName": "peacekeeping-east-timor-f6f",
        "path": "/peacekeeping-east-timor"
    },
    {
        "componentChunkName": "component---src-templates-single-js",
        "jsonName": "peacekeeping-out-of-africa-ba9",
        "path": "/peacekeeping-out-of-africa"
    },
    {
        "componentChunkName": "component---src-templates-single-js",
        "jsonName": "peacekeeping-overview-to-year-2000-d9a",
        "path": "/peacekeeping-overview-to-year-2000"
    },
    {
        "componentChunkName": "component---src-templates-single-js",
        "jsonName": "peacekeeping-supplementary-information-and-anecdotes-ea1",
        "path": "/peacekeeping-supplementary-information-and-anecdotes"
    },
    {
        "componentChunkName": "component---src-templates-single-js",
        "jsonName": "personal-testimony-1-253",
        "path": "/personal-testimony-1"
    },
    {
        "componentChunkName": "component---src-templates-single-js",
        "jsonName": "personal-testimony-2-79a",
        "path": "/personal-testimony-2"
    },
    {
        "componentChunkName": "component---src-templates-single-js",
        "jsonName": "personal-testimony-3-345",
        "path": "/personal-testimony-3"
    },
    {
        "componentChunkName": "component---src-templates-single-js",
        "jsonName": "personal-testimony-4-1f2",
        "path": "/personal-testimony-4"
    },
    {
        "componentChunkName": "component---src-templates-single-js",
        "jsonName": "personal-testimony-5-b1c",
        "path": "/personal-testimony-5"
    },
    {
        "componentChunkName": "component---src-templates-single-js",
        "jsonName": "personal-testimony-6-89c",
        "path": "/personal-testimony-6"
    },
    {
        "componentChunkName": "component---src-templates-single-js",
        "jsonName": "phoney-cbb",
        "path": "/phoney"
    },
    {
        "componentChunkName": "component---src-templates-single-js",
        "jsonName": "piecing-a-life-together-62c",
        "path": "/piecing-a-life-together"
    },
    {
        "componentChunkName": "component---src-templates-single-js",
        "jsonName": "poetry-4d1",
        "path": "/poetry"
    },
    {
        "componentChunkName": "component---src-templates-single-js",
        "jsonName": "poster-images-from-moretonbay-regional-council-fd6",
        "path": "/poster-images-from-moretonbay-regional-council"
    },
    {
        "componentChunkName": "component---src-templates-single-js",
        "jsonName": "prayers-for-anzac-day-services-eb2",
        "path": "/prayers-for-anzac-day-services"
    },
    {
        "componentChunkName": "component---src-templates-single-js",
        "jsonName": "prisoners-of-war-world-war-2-3f9",
        "path": "/prisoners-of-war-world-war-2"
    },
    {
        "componentChunkName": "component---src-templates-single-js",
        "jsonName": "privacy-policy-1cf",
        "path": "/privacy-policy"
    },
    {
        "componentChunkName": "component---src-templates-single-js",
        "jsonName": "private-arthur-stanley-gurney-798",
        "path": "/private-arthur-stanley-gurney"
    },
    {
        "componentChunkName": "component---src-templates-single-js",
        "jsonName": "private-bruce-steel-kingsbury-757",
        "path": "/private-bruce-steel-kingsbury"
    },
    {
        "componentChunkName": "component---src-templates-single-js",
        "jsonName": "private-edward-john-frances-ryan-4df",
        "path": "/private-edward-john-frances-ryan"
    },
    {
        "componentChunkName": "component---src-templates-single-js",
        "jsonName": "private-edward-kenna-c37",
        "path": "/private-edward-kenna"
    },
    {
        "componentChunkName": "component---src-templates-single-js",
        "jsonName": "private-frank-john-partridge-ecc",
        "path": "/private-frank-john-partridge"
    },
    {
        "componentChunkName": "component---src-templates-single-js",
        "jsonName": "private-george-cartwright-19d",
        "path": "/private-george-cartwright"
    },
    {
        "componentChunkName": "component---src-templates-single-js",
        "jsonName": "private-henry-dalziel-517",
        "path": "/private-henry-dalziel"
    },
    {
        "componentChunkName": "component---src-templates-single-js",
        "jsonName": "private-james-heather-gordon-1e8",
        "path": "/private-james-heather-gordon"
    },
    {
        "componentChunkName": "component---src-templates-single-js",
        "jsonName": "private-james-park-woods-764",
        "path": "/private-james-park-woods"
    },
    {
        "componentChunkName": "component---src-templates-single-js",
        "jsonName": "private-joergen-christian-jensen-49a",
        "path": "/private-joergen-christian-jensen"
    },
    {
        "componentChunkName": "component---src-templates-single-js",
        "jsonName": "private-john-carroll-9db",
        "path": "/private-john-carroll"
    },
    {
        "componentChunkName": "component---src-templates-single-js",
        "jsonName": "private-john-leak-f52",
        "path": "/private-john-leak"
    },
    {
        "componentChunkName": "component---src-templates-single-js",
        "jsonName": "private-john-patrick-hamilton-4a7",
        "path": "/private-john-patrick-hamilton"
    },
    {
        "componentChunkName": "component---src-templates-single-js",
        "jsonName": "private-john-william-alexander-jackson-e05",
        "path": "/private-john-william-alexander-jackson"
    },
    {
        "componentChunkName": "component---src-templates-single-js",
        "jsonName": "private-leslie-thomas-starcevich-3a3",
        "path": "/private-leslie-thomas-starcevich"
    },
    {
        "componentChunkName": "component---src-templates-single-js",
        "jsonName": "private-martin-omeara-1ed",
        "path": "/private-martin-omeara"
    },
    {
        "componentChunkName": "component---src-templates-single-js",
        "jsonName": "private-patrick-joseph-bugden-fdb",
        "path": "/private-patrick-joseph-bugden"
    },
    {
        "componentChunkName": "component---src-templates-single-js",
        "jsonName": "private-percival-eric-gratwick-ee3",
        "path": "/private-percival-eric-gratwick"
    },
    {
        "componentChunkName": "component---src-templates-single-js",
        "jsonName": "private-reginald-roy-inwood-997",
        "path": "/private-reginald-roy-inwood"
    },
    {
        "componentChunkName": "component---src-templates-single-js",
        "jsonName": "private-richard-kelliher-4b2",
        "path": "/private-richard-kelliher"
    },
    {
        "componentChunkName": "component---src-templates-single-js",
        "jsonName": "private-robert-mactier-a18",
        "path": "/private-robert-mactier"
    },
    {
        "componentChunkName": "component---src-templates-single-js",
        "jsonName": "private-robert-matthew-beatham-2b9",
        "path": "/private-robert-matthew-beatham"
    },
    {
        "componentChunkName": "component---src-templates-single-js",
        "jsonName": "private-thomas-cooke-da2",
        "path": "/private-thomas-cooke"
    },
    {
        "componentChunkName": "component---src-templates-single-js",
        "jsonName": "private-thomas-james-bede-kenny-4fb",
        "path": "/private-thomas-james-bede-kenny"
    },
    {
        "componentChunkName": "component---src-templates-single-js",
        "jsonName": "private-william-matthew-currey-d86",
        "path": "/private-william-matthew-currey"
    },
    {
        "componentChunkName": "component---src-templates-single-js",
        "jsonName": "q-is-for-questions-671",
        "path": "/q-is-for-questions"
    },
    {
        "componentChunkName": "component---src-templates-single-js",
        "jsonName": "r-is-for-rising-sun-e6d",
        "path": "/r-is-for-rising-sun"
    },
    {
        "componentChunkName": "component---src-templates-single-js",
        "jsonName": "remembering-and-commemorating-0ea",
        "path": "/remembering-and-commemorating"
    },
    {
        "componentChunkName": "component---src-templates-single-js",
        "jsonName": "rosemary-is-for-remembrance-bbc",
        "path": "/rosemary-is-for-remembrance"
    },
    {
        "componentChunkName": "component---src-templates-single-js",
        "jsonName": "s-is-for-simpson-and-his-donkey-ef3",
        "path": "/s-is-for-simpson-and-his-donkey"
    },
    {
        "componentChunkName": "component---src-templates-single-js",
        "jsonName": "sanananda-7aa",
        "path": "/sanananda"
    },
    {
        "componentChunkName": "component---src-templates-single-js",
        "jsonName": "second-lieutenant-hugo-vivian-hope-throssell-246",
        "path": "/second-lieutenant-hugo-vivian-hope-throssell"
    },
    {
        "componentChunkName": "component---src-templates-single-js",
        "jsonName": "selected-ww-1-statistics-b5f",
        "path": "/selected-WW1-statistics"
    },
    {
        "componentChunkName": "component---src-templates-single-js",
        "jsonName": "sergeant-albert-david-lowerson-5db",
        "path": "/sergeant-albert-david-lowerson"
    },
    {
        "componentChunkName": "component---src-templates-single-js",
        "jsonName": "sergeant-claud-charles-castleton-2ec",
        "path": "/sergeant-claud-charles-castleton"
    },
    {
        "componentChunkName": "component---src-templates-single-js",
        "jsonName": "sergeant-james-rogers-d05",
        "path": "/sergeant-james-rogers"
    },
    {
        "componentChunkName": "component---src-templates-single-js",
        "jsonName": "sergeant-john-james-dwyer-bcf",
        "path": "/sergeant-john-james-dwyer"
    },
    {
        "componentChunkName": "component---src-templates-single-js",
        "jsonName": "sergeant-john-woods-whittle-a1e",
        "path": "/sergeant-john-woods-whittle"
    },
    {
        "componentChunkName": "component---src-templates-single-js",
        "jsonName": "sergeant-lewis-mcgee-cb0",
        "path": "/sergeant-lewis-mcgee"
    },
    {
        "componentChunkName": "component---src-templates-single-js",
        "jsonName": "sergeant-maurice-vincent-buckley-7b7",
        "path": "/sergeant-maurice-vincent-buckley"
    },
    {
        "componentChunkName": "component---src-templates-single-js",
        "jsonName": "sergeant-percy-clyde-statton-735",
        "path": "/sergeant-percy-clyde-statton"
    },
    {
        "componentChunkName": "component---src-templates-single-js",
        "jsonName": "sergeant-samuel-george-pearse-c9c",
        "path": "/sergeant-samuel-george-pearse"
    },
    {
        "componentChunkName": "component---src-templates-single-js",
        "jsonName": "sergeant-stanley-robert-mcdougall-81b",
        "path": "/sergeant-stanley-robert-mcdougall"
    },
    {
        "componentChunkName": "component---src-templates-single-js",
        "jsonName": "sergeant-thomas-currie-derrick-82f",
        "path": "/sergeant-thomas-currie-derrick"
    },
    {
        "componentChunkName": "component---src-templates-single-js",
        "jsonName": "sergeant-william-henry-kibby-ea6",
        "path": "/sergeant-william-henry-kibby"
    },
    {
        "componentChunkName": "component---src-templates-single-js",
        "jsonName": "sergeant-william-ruthven-3e8",
        "path": "/sergeant-william-ruthven"
    },
    {
        "componentChunkName": "component---src-templates-single-js",
        "jsonName": "service-activities-829",
        "path": "/service-activities"
    },
    {
        "componentChunkName": "component---src-templates-single-js",
        "jsonName": "service-outline-8b4",
        "path": "/service-outline"
    },
    {
        "componentChunkName": "component---src-templates-single-js",
        "jsonName": "sheet-music-for-bugle-calls-909",
        "path": "/sheet-music-for-bugle-calls"
    },
    {
        "componentChunkName": "component---src-templates-single-js",
        "jsonName": "should-we-remember-weary-dunlop-6b7",
        "path": "/should-we-remember-weary-dunlop"
    },
    {
        "componentChunkName": "component---src-templates-single-js",
        "jsonName": "shrine-of-remembrance-anzac-square-brisbane-dcc",
        "path": "/shrine-of-remembrance-anzac-square-brisbane"
    },
    {
        "componentChunkName": "component---src-templates-single-js",
        "jsonName": "shrine-of-remembrance-melbourne-169",
        "path": "/shrine-of-remembrance-melbourne"
    },
    {
        "componentChunkName": "component---src-templates-single-js",
        "jsonName": "simpson-and-his-donkey-871",
        "path": "/simpson-and-his-donkey"
    },
    {
        "componentChunkName": "component---src-templates-single-js",
        "jsonName": "sir-1a2",
        "path": "/sir"
    },
    {
        "componentChunkName": "component---src-templates-single-js",
        "jsonName": "sloan-bolton-dcm-diary-708",
        "path": "/sloan-bolton-dcm-diary"
    },
    {
        "componentChunkName": "component---src-templates-single-js",
        "jsonName": "sloan-bolton-dcm-family-tree-97c",
        "path": "/sloan-bolton-dcm-family-tree"
    },
    {
        "componentChunkName": "component---src-templates-single-js",
        "jsonName": "smithy-interactive-59d",
        "path": "/smithy-interactive"
    },
    {
        "componentChunkName": "component---src-templates-single-js",
        "jsonName": "smithy-introduction-869",
        "path": "/smithy-introduction"
    },
    {
        "componentChunkName": "component---src-templates-single-js",
        "jsonName": "snippets-korean-war-9ed",
        "path": "/snippets-korean-war"
    },
    {
        "componentChunkName": "component---src-templates-single-js",
        "jsonName": "snow-bound-727",
        "path": "/snow-bound"
    },
    {
        "componentChunkName": "component---src-templates-single-js",
        "jsonName": "soldiers-of-the-cross-409",
        "path": "/soldiers-of-the-cross"
    },
    {
        "componentChunkName": "component---src-templates-single-js",
        "jsonName": "soldiers-on-the-stone-and-other-queensland-memorials-797",
        "path": "/soldiers-on-the-stone-and-other-queensland-memorials"
    },
    {
        "componentChunkName": "component---src-templates-single-js",
        "jsonName": "somalia-1993-1996-8f3",
        "path": "/somalia-1993--1996"
    },
    {
        "componentChunkName": "component---src-templates-single-js",
        "jsonName": "sonnet-for-anzac-day-4f6",
        "path": "/sonnet-for-anzac-day"
    },
    {
        "componentChunkName": "component---src-templates-single-js",
        "jsonName": "sources-168",
        "path": "/sources"
    },
    {
        "componentChunkName": "component---src-templates-single-js",
        "jsonName": "speeches-a00",
        "path": "/speeches"
    },
    {
        "componentChunkName": "component---src-templates-single-js",
        "jsonName": "spirit-gallipoli-campaign-e25",
        "path": "/spirit-gallipoli-campaign"
    },
    {
        "componentChunkName": "component---src-templates-single-js",
        "jsonName": "spirit-of-anzac-278",
        "path": "/spirit-of-anzac"
    },
    {
        "componentChunkName": "component---src-templates-single-js",
        "jsonName": "spirit-where-anzacs-lie-cac",
        "path": "/spirit-where-anzacs-lie"
    },
    {
        "componentChunkName": "component---src-templates-single-js",
        "jsonName": "state-war-memorial-cenotaph-perth-52c",
        "path": "/state-war-memorial-cenotaph-perth"
    },
    {
        "componentChunkName": "component---src-templates-single-js",
        "jsonName": "statement-by-escaped-prisoner-owen-campbell-1bb",
        "path": "/statement-by-escaped-prisoner-owen-campbell"
    },
    {
        "componentChunkName": "component---src-templates-single-js",
        "jsonName": "success-and-failure-in-the-port-of-singapore-z-special-unit-and-the-jaywick-and-rimau-raids-97a",
        "path": "/success-and-failure-in-the-port-of-singapore-z-special-unit-and-the-jaywick-and-rimau-raids"
    },
    {
        "componentChunkName": "component---src-templates-single-js",
        "jsonName": "suitcase-treasure-ce2",
        "path": "/suitcase-treasure"
    },
    {
        "componentChunkName": "component---src-templates-single-js",
        "jsonName": "supporting-material-for-the-adcc-publication-in-search-of-jacka-vc-d77",
        "path": "/supporting-material-for-the-adcc-publication-in-search-of-jacka-vc"
    },
    {
        "componentChunkName": "component---src-templates-single-js",
        "jsonName": "survival-and-health-9f5",
        "path": "/survival-and-health"
    },
    {
        "componentChunkName": "component---src-templates-single-js",
        "jsonName": "survivors-33e",
        "path": "/survivors"
    },
    {
        "componentChunkName": "component---src-templates-single-js",
        "jsonName": "t-is-for-the-tomb-of-the-unknown-australian-soldier-dc1",
        "path": "/t-is-for-the-tomb-of-the-unknown-australian-soldier"
    },
    {
        "componentChunkName": "component---src-templates-single-js",
        "jsonName": "tackling-some-myths-and-misunderstandings-of-the-vietnam-war-7fa",
        "path": "/tackling-some-myths-and-misunderstandings-of-the-vietnam-war"
    },
    {
        "componentChunkName": "component---src-templates-single-js",
        "jsonName": "teachers-guide-12c",
        "path": "/teachers-guide"
    },
    {
        "componentChunkName": "component---src-templates-single-js",
        "jsonName": "teacup-in-a-storm-cb3",
        "path": "/teacup-in-a-storm"
    },
    {
        "componentChunkName": "component---src-templates-single-js",
        "jsonName": "temporary-corporal-alexander-henry-buckley-fa0",
        "path": "/temporary-corporal-alexander-henry-buckley"
    },
    {
        "componentChunkName": "component---src-templates-single-js",
        "jsonName": "temporary-corporal-lawrence-carthage-weathers-3b9",
        "path": "/temporary-corporal-lawrence-carthage-weathers"
    },
    {
        "componentChunkName": "component---src-templates-single-js",
        "jsonName": "temporary-lieutenant-william-thomas-dartnell-16d",
        "path": "/temporary-lieutenant-william-thomas-dartnell"
    },
    {
        "componentChunkName": "component---src-templates-single-js",
        "jsonName": "terms-8b2",
        "path": "/terms"
    },
    {
        "componentChunkName": "component---src-templates-single-js",
        "jsonName": "the-anzacs-day-25-april-1915-e5d",
        "path": "/the-anzacs-day-25-april-1915"
    },
    {
        "componentChunkName": "component---src-templates-single-js",
        "jsonName": "the-australian-423",
        "path": "/the-australian"
    },
    {
        "componentChunkName": "component---src-templates-single-js",
        "jsonName": "the-australian-home-front-during-world-war-1-558",
        "path": "/the-australian-home-front-during-world-war1"
    },
    {
        "componentChunkName": "component---src-templates-single-js",
        "jsonName": "the-australian-national-flag-c82",
        "path": "/the-australian-national-flag"
    },
    {
        "componentChunkName": "component---src-templates-single-js",
        "jsonName": "the-australian-war-memorial-219",
        "path": "/the-australian-war-memorial"
    },
    {
        "componentChunkName": "component---src-templates-single-js",
        "jsonName": "the-battle-of-the-coral-sea-did-it-save-australia-9cc",
        "path": "/the-battle-of-the-coral-sea-did-it-save-australia"
    },
    {
        "componentChunkName": "component---src-templates-single-js",
        "jsonName": "the-bitter-truth-883",
        "path": "/the-bitter-truth"
    },
    {
        "componentChunkName": "component---src-templates-single-js",
        "jsonName": "the-catafalque-party-f8f",
        "path": "/the-catafalque-party"
    },
    {
        "componentChunkName": "component---src-templates-single-js",
        "jsonName": "the-clown-prince-6f6",
        "path": "/the-clown-prince"
    },
    {
        "componentChunkName": "component---src-templates-single-js",
        "jsonName": "the-dawn-service-e2f",
        "path": "/the-dawn-service"
    },
    {
        "componentChunkName": "component---src-templates-single-js",
        "jsonName": "the-donkey-bea",
        "path": "/the-donkey"
    },
    {
        "componentChunkName": "component---src-templates-single-js",
        "jsonName": "the-evidence-of-australian-prisoners-6cf",
        "path": "/the-evidence-of-australian-prisoners"
    },
    {
        "componentChunkName": "component---src-templates-single-js",
        "jsonName": "the-evidence-of-japanese-guards-330",
        "path": "/the-evidence-of-japanese-guards"
    },
    {
        "componentChunkName": "component---src-templates-single-js",
        "jsonName": "the-evidence-of-local-people-52b",
        "path": "/the-evidence-of-local-people"
    },
    {
        "componentChunkName": "component---src-templates-single-js",
        "jsonName": "the-evidence-of-physical-remains-233",
        "path": "/the-evidence-of-physical-remains"
    },
    {
        "componentChunkName": "component---src-templates-single-js",
        "jsonName": "the-fuzzy-wuzzy-angels-153",
        "path": "/the-fuzzy-wuzzy-angels"
    },
    {
        "componentChunkName": "component---src-templates-single-js",
        "jsonName": "the-home-front-world-war-2-b1d",
        "path": "/the-home-front-world-war-2"
    },
    {
        "componentChunkName": "component---src-templates-single-js",
        "jsonName": "the-human-lottery-7f9",
        "path": "/the-human-lottery"
    },
    {
        "componentChunkName": "component---src-templates-single-js",
        "jsonName": "the-lady-southern-cross-is-missing-investigating-theories-1-and-2-eb4",
        "path": "/the-lady-southern-cross-is-missing-investigating-theories-1-and-2"
    },
    {
        "componentChunkName": "component---src-templates-single-js",
        "jsonName": "the-lady-southern-cross-is-missing-investigating-theory-3-5db",
        "path": "/the-lady-southern-cross-is-missing-investigating-theory-3"
    },
    {
        "componentChunkName": "component---src-templates-single-js",
        "jsonName": "the-landing-d3e",
        "path": "/the-landing"
    },
    {
        "componentChunkName": "component---src-templates-single-js",
        "jsonName": "the-last-gallipoli-anzac-constructing-a-biography-of-alec-campbell-88f",
        "path": "/the-last-gallipoli-anzac-constructing-a-biography-of-alec-campbell"
    },
    {
        "componentChunkName": "component---src-templates-single-js",
        "jsonName": "the-light-horse-8a7",
        "path": "/the-light-horse"
    },
    {
        "componentChunkName": "component---src-templates-single-js",
        "jsonName": "the-long-tan-cross-838",
        "path": "/the-long-tan-cross"
    },
    {
        "componentChunkName": "component---src-templates-single-js",
        "jsonName": "the-military-salute-c4a",
        "path": "/the-military-salute"
    },
    {
        "componentChunkName": "component---src-templates-single-js",
        "jsonName": "the-origin-of-the-acronym-anzac-003",
        "path": "/the-origin-of-the-acronym-anzac"
    },
    {
        "componentChunkName": "component---src-templates-single-js",
        "jsonName": "the-poppy-is-for-sacrifice-446",
        "path": "/the-poppy-is-for-sacrifice"
    },
    {
        "componentChunkName": "component---src-templates-single-js",
        "jsonName": "the-region-and-its-history-easttimor-68f",
        "path": "/the-region-and-its-history-easttimor"
    },
    {
        "componentChunkName": "component---src-templates-single-js",
        "jsonName": "the-rising-sun-badge-55c",
        "path": "/the-rising-sun-badge"
    },
    {
        "componentChunkName": "component---src-templates-single-js",
        "jsonName": "the-sinking-of-the-australian-hospital-ship-centaur-war-crime-or-legitimate-target-357",
        "path": "/the-sinking-of-the-australian-hospital-ship-centaur-war-crime-or-legitimate-target"
    },
    {
        "componentChunkName": "component---src-templates-single-js",
        "jsonName": "the-slouch-hat-and-emu-plumes-c72",
        "path": "/the-slouch-hat-and-emu-plumes"
    },
    {
        "componentChunkName": "component---src-templates-single-js",
        "jsonName": "the-soul-of-australia-70c",
        "path": "/the-soul-of-australia"
    },
    {
        "componentChunkName": "component---src-templates-single-js",
        "jsonName": "the-spirit-of-anzac-adf",
        "path": "/the-spirit-of-anzac"
    },
    {
        "componentChunkName": "component---src-templates-single-js",
        "jsonName": "the-task-5d9",
        "path": "/the-task"
    },
    {
        "componentChunkName": "component---src-templates-single-js",
        "jsonName": "the-tomb-of-the-unknown-australian-soldier-c28",
        "path": "/the-tomb-of-the-unknown-australian-soldier"
    },
    {
        "componentChunkName": "component---src-templates-single-js",
        "jsonName": "the-uniform-resolution-bce",
        "path": "/the-uniform-resolution"
    },
    {
        "componentChunkName": "component---src-templates-single-js",
        "jsonName": "the-victoria-cross-1-7ce",
        "path": "/the-victoria-cross-1"
    },
    {
        "componentChunkName": "component---src-templates-single-js",
        "jsonName": "the-victoria-cross-main-905",
        "path": "/the-victoria-cross-main"
    },
    {
        "componentChunkName": "component---src-templates-single-js",
        "jsonName": "the-war-in-europe-6ff",
        "path": "/the-war-in-europe"
    },
    {
        "componentChunkName": "component---src-templates-single-js",
        "jsonName": "the-war-in-north-africa-the-mediterranean-and-the-middle-east-45b",
        "path": "/the-war-in-north-africa-the-mediterranean-and-the-middle-east"
    },
    {
        "componentChunkName": "component---src-templates-single-js",
        "jsonName": "the-war-on-all-fronts-year-by-year-bac",
        "path": "/the-war-on-all-fronts-year-by-year"
    },
    {
        "componentChunkName": "component---src-templates-single-js",
        "jsonName": "the-war-on-the-home-front-and-in-australian-waters-00d",
        "path": "/the-war-on-the-home-front-and-in-australian-waters"
    },
    {
        "componentChunkName": "component---src-templates-single-js",
        "jsonName": "themes-74f",
        "path": "/themes"
    },
    {
        "componentChunkName": "component---src-templates-single-js",
        "jsonName": "to-the-sunburnt-ear-e29",
        "path": "/to-the-sunburnt-ear"
    },
    {
        "componentChunkName": "component---src-templates-single-js",
        "jsonName": "townsville-9b9",
        "path": "/townsville"
    },
    {
        "componentChunkName": "component---src-templates-single-js",
        "jsonName": "traditions-facts-and-folklore-15e",
        "path": "/traditions-facts-and-folklore"
    },
    {
        "componentChunkName": "component---src-templates-single-js",
        "jsonName": "training-1ee",
        "path": "/training"
    },
    {
        "componentChunkName": "component---src-templates-single-js",
        "jsonName": "trooper-john-hutton-bisdee-0f7",
        "path": "/trooper-john-hutton-bisdee"
    },
    {
        "componentChunkName": "component---src-templates-single-js",
        "jsonName": "trooper-sloan-scotty-bolton-dcm-c17",
        "path": "/trooper-sloan-scotty-bolton-dcm"
    },
    {
        "componentChunkName": "component---src-templates-single-js",
        "jsonName": "two-events-of-1943-305",
        "path": "/two-events-of-1943"
    },
    {
        "componentChunkName": "component---src-templates-single-js",
        "jsonName": "tyneside-ea9",
        "path": "/tyneside"
    },
    {
        "componentChunkName": "component---src-templates-single-js",
        "jsonName": "typhoon-ruth-bd0",
        "path": "/typhoon-ruth"
    },
    {
        "componentChunkName": "component---src-templates-single-js",
        "jsonName": "u-is-for-uniforms-d2f",
        "path": "/u-is-for-uniforms"
    },
    {
        "componentChunkName": "component---src-templates-single-js",
        "jsonName": "uniforms-over-time-886",
        "path": "/uniforms-over-time"
    },
    {
        "componentChunkName": "component---src-templates-single-js",
        "jsonName": "useful-local-contacts-and-resources-317",
        "path": "/useful-local-contacts-and-resources"
    },
    {
        "componentChunkName": "component---src-templates-single-js",
        "jsonName": "useful-websites-68c",
        "path": "/useful-websites"
    },
    {
        "componentChunkName": "component---src-templates-single-js",
        "jsonName": "v-is-for-villers-bretonneux-bret-on-er-385",
        "path": "/v-is-for-villers-bretonneux-bret-on-er"
    },
    {
        "componentChunkName": "component---src-templates-single-js",
        "jsonName": "victoria-cross-064",
        "path": "/victoria-cross"
    },
    {
        "componentChunkName": "component---src-templates-single-js",
        "jsonName": "vietnam-dogs-of-war-675",
        "path": "/vietnam-dogs-of-war"
    },
    {
        "componentChunkName": "component---src-templates-single-js",
        "jsonName": "vietnam-the-soldiers-experience-d89",
        "path": "/vietnam-the-soldiers-experience"
    },
    {
        "componentChunkName": "component---src-templates-single-js",
        "jsonName": "vietnam-the-spirit-of-an-anzac-3d2",
        "path": "/vietnam-the-spirit-of-an-anzac"
    },
    {
        "componentChunkName": "component---src-templates-single-js",
        "jsonName": "vietnam-war-794",
        "path": "/vietnam-war"
    },
    {
        "componentChunkName": "component---src-templates-single-js",
        "jsonName": "vietnam-war-australian-casualties-f98",
        "path": "/vietnam-war-australian-casualties"
    },
    {
        "componentChunkName": "component---src-templates-single-js",
        "jsonName": "vietnam-war-overview-461",
        "path": "/vietnam-war-overview"
    },
    {
        "componentChunkName": "component---src-templates-single-js",
        "jsonName": "vietnam-war-supplementary-information-and-anecdotes-8df",
        "path": "/vietnam-war-supplementary-information-and-anecdotes"
    },
    {
        "componentChunkName": "component---src-templates-single-js",
        "jsonName": "view-print-be2",
        "path": "/view-print"
    },
    {
        "componentChunkName": "component---src-templates-single-js",
        "jsonName": "volunteer-152",
        "path": "/volunteer"
    },
    {
        "componentChunkName": "component---src-templates-single-js",
        "jsonName": "w-is-for-war-memorials-47d",
        "path": "/w-is-for-war-memorials"
    },
    {
        "componentChunkName": "component---src-templates-single-js",
        "jsonName": "war-and-identity-5ae",
        "path": "/war-and-identity"
    },
    {
        "componentChunkName": "component---src-templates-single-js",
        "jsonName": "war-in-the-air-85d",
        "path": "/war-in-the-air"
    },
    {
        "componentChunkName": "component---src-templates-single-js",
        "jsonName": "war-memorials-7d3",
        "path": "/war-memorials"
    },
    {
        "componentChunkName": "component---src-templates-single-js",
        "jsonName": "warathome-13f",
        "path": "/warathome"
    },
    {
        "componentChunkName": "component---src-templates-single-js",
        "jsonName": "warrant-officer-class-ii-keith-payne-77e",
        "path": "/warrant-officer-class-ii-keith-payne"
    },
    {
        "componentChunkName": "component---src-templates-single-js",
        "jsonName": "warrant-officer-class-ii-kevin-arthur-wheatley-5c9",
        "path": "/warrant-officer-class-ii-kevin-arthur-wheatley"
    },
    {
        "componentChunkName": "component---src-templates-single-js",
        "jsonName": "warrant-officer-class-ii-rayene-stewart-simpson-2fa",
        "path": "/warrant-officer-class-ii-rayene-stewart-simpson"
    },
    {
        "componentChunkName": "component---src-templates-single-js",
        "jsonName": "wars-570",
        "path": "/wars"
    },
    {
        "componentChunkName": "component---src-templates-single-js",
        "jsonName": "welcome-to-the-anzac-day-commemoration-committee-of-queensland-site-50f",
        "path": "/welcome-to-the-anzac-day-commemoration-committee-of-queensland-site"
    },
    {
        "componentChunkName": "component---src-templates-single-js",
        "jsonName": "were-all-australians-now-b01",
        "path": "/were-all-australians-now"
    },
    {
        "componentChunkName": "component---src-templates-single-js",
        "jsonName": "were-australians-fighting-an-other-peoples-war-in-vietnam-f39",
        "path": "/were-australians-fighting-an-other-peoples-war-in-vietnam"
    },
    {
        "componentChunkName": "component---src-templates-single-js",
        "jsonName": "were-most-australian-deaths-in-the-vietnam-war-from-combat-with-the-enemy-b88",
        "path": "/were-most-australian-deaths-in-the-vietnam-war-from-combat-with-the-enemy"
    },
    {
        "componentChunkName": "component---src-templates-single-js",
        "jsonName": "what-happened-during-the-war-an-overview-46c",
        "path": "/what-happened-during-the-war-an-overview"
    },
    {
        "componentChunkName": "component---src-templates-single-js",
        "jsonName": "what-happened-to-smithy-three-theories-8b5",
        "path": "/what-happened-to-smithy-three-theories"
    },
    {
        "componentChunkName": "component---src-templates-single-js",
        "jsonName": "where-in-the-world-c1a",
        "path": "/where-in-the-world"
    },
    {
        "componentChunkName": "component---src-templates-single-js",
        "jsonName": "who-am-i-8e3",
        "path": "/who-am-i"
    },
    {
        "componentChunkName": "component---src-templates-single-js",
        "jsonName": "why-did-the-crash-occur-creating-your-own-storyboard-e7c",
        "path": "/why-did-the-crash-occur-creating-your-own-storyboard"
    },
    {
        "componentChunkName": "component---src-templates-single-js",
        "jsonName": "witness-to-genocide-a-personal-account-of-the-1995-kibeho-massacre-18e",
        "path": "/witness-to-genocide-a-personal-account-of-the-1995-kibeho-massacre"
    },
    {
        "componentChunkName": "component---src-templates-single-js",
        "jsonName": "women-e10",
        "path": "/women"
    },
    {
        "componentChunkName": "component---src-templates-single-js",
        "jsonName": "women-in-the-australian-defence-force-do-they-have-an-equal-role-to-men-ee9",
        "path": "/women-in-the-australian-defence-force-do-they-have-an-equal-role-to-men"
    },
    {
        "componentChunkName": "component---src-templates-single-js",
        "jsonName": "women-in-war-8b1",
        "path": "/women-in-war"
    },
    {
        "componentChunkName": "component---src-templates-single-js",
        "jsonName": "womens-services-in-world-war-2-827",
        "path": "/womens-services-in-world-war-2"
    },
    {
        "componentChunkName": "component---src-templates-single-js",
        "jsonName": "womens-role-and-place-0e1",
        "path": "/women’s-role-and-place"
    },
    {
        "componentChunkName": "component---src-templates-single-js",
        "jsonName": "words-of-remembrance-24e",
        "path": "/words-of-remembrance"
    },
    {
        "componentChunkName": "component---src-templates-single-js",
        "jsonName": "ww-1-439",
        "path": "/ww1"
    },
    {
        "componentChunkName": "component---src-templates-single-js",
        "jsonName": "ww-1-anzac-biscuits-647",
        "path": "/ww1-ANZAC-biscuits"
    },
    {
        "componentChunkName": "component---src-templates-single-js",
        "jsonName": "ww-1-at-sea-762",
        "path": "/ww1-at-sea"
    },
    {
        "componentChunkName": "component---src-templates-single-js",
        "jsonName": "ww-1-casualty-clearance-258",
        "path": "/ww1-casualty-clearance"
    },
    {
        "componentChunkName": "component---src-templates-single-js",
        "jsonName": "ww-1-cominghome-856",
        "path": "/ww1-cominghome"
    },
    {
        "componentChunkName": "component---src-templates-single-js",
        "jsonName": "ww-1-gallipoli-91d",
        "path": "/ww1-gallipoli"
    },
    {
        "componentChunkName": "component---src-templates-single-js",
        "jsonName": "ww-1-general-5f8",
        "path": "/ww1-general"
    },
    {
        "componentChunkName": "component---src-templates-single-js",
        "jsonName": "ww-1-home-front-b84",
        "path": "/ww1-home-front"
    },
    {
        "componentChunkName": "component---src-templates-single-js",
        "jsonName": "ww-1-in-the-air-b8e",
        "path": "/ww1-in-the-air"
    },
    {
        "componentChunkName": "component---src-templates-single-js",
        "jsonName": "ww-1-just-soldiers-83f",
        "path": "/ww1-just-soldiers"
    },
    {
        "componentChunkName": "component---src-templates-single-js",
        "jsonName": "ww-1-lt-cdr-henry-stoker-68d",
        "path": "/ww1-lt-cdr-henry-stoker"
    },
    {
        "componentChunkName": "component---src-templates-single-js",
        "jsonName": "ww-1-middle-east-858",
        "path": "/ww1-middle-east"
    },
    {
        "componentChunkName": "component---src-templates-single-js",
        "jsonName": "ww-1-overview-4e8",
        "path": "/ww1-overview"
    },
    {
        "componentChunkName": "component---src-templates-single-js",
        "jsonName": "ww-1-pioneers-of-the-air-488",
        "path": "/ww1-pioneers-of-the-air"
    },
    {
        "componentChunkName": "component---src-templates-single-js",
        "jsonName": "ww-1-supplementary-information-and-anecdotes-711",
        "path": "/ww1-supplementary-information-and-anecdotes"
    },
    {
        "componentChunkName": "component---src-templates-single-js",
        "jsonName": "ww-1-the-campaign-in-the-middle-east-b1d",
        "path": "/ww1-the-campaign-in-the-middle-east"
    },
    {
        "componentChunkName": "component---src-templates-single-js",
        "jsonName": "ww-1-the-gallipoli-campaign-0db",
        "path": "/ww1-the-gallipoli-campaign"
    },
    {
        "componentChunkName": "component---src-templates-single-js",
        "jsonName": "ww-1-the-nurses-f4c",
        "path": "/ww1-the-nurses"
    },
    {
        "componentChunkName": "component---src-templates-single-js",
        "jsonName": "ww-1-the-war-at-sea-ea0",
        "path": "/ww1-the-war-at-sea"
    },
    {
        "componentChunkName": "component---src-templates-single-js",
        "jsonName": "ww-1-the-western-front-0e6",
        "path": "/ww1-the-western-front"
    },
    {
        "componentChunkName": "component---src-templates-single-js",
        "jsonName": "ww-1-western-front-bd2",
        "path": "/ww1-western-front"
    },
    {
        "componentChunkName": "component---src-templates-single-js",
        "jsonName": "ww-2-1942-an-overview-of-the-battle-for-australia-354",
        "path": "/ww2-1942-an-overview-of-the-battle-for-australia"
    },
    {
        "componentChunkName": "component---src-templates-single-js",
        "jsonName": "ww-2-americans-5de",
        "path": "/ww2-americans"
    },
    {
        "componentChunkName": "component---src-templates-single-js",
        "jsonName": "ww-2-asia-pacific-ba1",
        "path": "/ww2-asia-pacific"
    },
    {
        "componentChunkName": "component---src-templates-single-js",
        "jsonName": "ww-2-australia-under-attack-b81",
        "path": "/ww2-australia-under-attack"
    },
    {
        "componentChunkName": "component---src-templates-single-js",
        "jsonName": "ww-2-battle-of-the-coral-sea-302",
        "path": "/ww2-battle-of-the-coral-sea"
    },
    {
        "componentChunkName": "component---src-templates-single-js",
        "jsonName": "ww-2-conscription-32b",
        "path": "/ww2-conscription"
    },
    {
        "componentChunkName": "component---src-templates-single-js",
        "jsonName": "ww-2-economy-576",
        "path": "/ww2-economy"
    },
    {
        "componentChunkName": "component---src-templates-single-js",
        "jsonName": "ww-2-europe-middle-east-121",
        "path": "/ww2-europe-middle-east"
    },
    {
        "componentChunkName": "component---src-templates-single-js",
        "jsonName": "ww-2-general-4cb",
        "path": "/ww2-general"
    },
    {
        "componentChunkName": "component---src-templates-single-js",
        "jsonName": "ww-2-home-front-543",
        "path": "/ww2-home-front"
    },
    {
        "componentChunkName": "component---src-templates-single-js",
        "jsonName": "ww-2-homefront-731",
        "path": "/ww2-homefront"
    },
    {
        "componentChunkName": "component---src-templates-single-js",
        "jsonName": "ww-2-indigenous-australians-07a",
        "path": "/ww2-indigenous-australians"
    },
    {
        "componentChunkName": "component---src-templates-single-js",
        "jsonName": "ww-2-initial-reactions-b9e",
        "path": "/ww2-initial-reactions"
    },
    {
        "componentChunkName": "component---src-templates-single-js",
        "jsonName": "ww-2-national-identity-6c9",
        "path": "/ww2-national-identity"
    },
    {
        "componentChunkName": "component---src-templates-single-js",
        "jsonName": "ww-2-on-a-wing-and-a-prayer-982",
        "path": "/ww2-on-a-wing-and-a-prayer"
    },
    {
        "componentChunkName": "component---src-templates-single-js",
        "jsonName": "ww-2-overview-140",
        "path": "/ww2-overview"
    },
    {
        "componentChunkName": "component---src-templates-single-js",
        "jsonName": "ww-2-prisoner-of-war-a67",
        "path": "/ww2-prisoner-of-war"
    },
    {
        "componentChunkName": "component---src-templates-single-js",
        "jsonName": "ww-2-striking-by-night-efc",
        "path": "/ww2-striking-by-night"
    },
    {
        "componentChunkName": "component---src-templates-single-js",
        "jsonName": "ww-2-supplementary-information-and-anecdotes-b98",
        "path": "/ww2-supplementary-information-and-anecdotes"
    },
    {
        "componentChunkName": "component---src-templates-single-js",
        "jsonName": "ww-2-the-battle-for-australia-a46",
        "path": "/ww2-the-battle-for-australia"
    },
    {
        "componentChunkName": "component---src-templates-single-js",
        "jsonName": "ww-2-the-battle-of-the-coral-sea-67f",
        "path": "/ww2-the-battle-of-the-coral-sea"
    },
    {
        "componentChunkName": "component---src-templates-single-js",
        "jsonName": "ww-2-the-unsung-heroes-of-the-sea-346",
        "path": "/ww2-the-unsung-heroes-of-the-sea"
    },
    {
        "componentChunkName": "component---src-templates-single-js",
        "jsonName": "ww-2-the-war-in-asia-and-the-pacific-54c",
        "path": "/ww2-the-war-in-asia-and-the-pacific"
    },
    {
        "componentChunkName": "component---src-templates-single-js",
        "jsonName": "ww-2-timor-8e5",
        "path": "/ww2-timor"
    },
    {
        "componentChunkName": "component---src-templates-single-js",
        "jsonName": "ww-2-tobruk-4b1",
        "path": "/ww2-tobruk"
    },
    {
        "componentChunkName": "component---src-templates-single-js",
        "jsonName": "ww-2-war-at-sea-3cb",
        "path": "/ww2-war-at-sea"
    },
    {
        "componentChunkName": "component---src-templates-single-js",
        "jsonName": "ww-2-women-0e5",
        "path": "/ww2-women"
    },
    {
        "componentChunkName": "component---src-templates-single-js",
        "jsonName": "www-1-the-toc-h-movement-118",
        "path": "/www1-the-toc-h-movement"
    },
    {
        "componentChunkName": "component---src-templates-single-js",
        "jsonName": "www-2-88d",
        "path": "/www2"
    },
    {
        "componentChunkName": "component---src-templates-single-js",
        "jsonName": "x-is-for-xenyl-chloride-a-poisonous-gas-f1c",
        "path": "/x-is-for-xenyl-chloride-a-poisonous-gas"
    },
    {
        "componentChunkName": "component---src-templates-single-js",
        "jsonName": "y-is-for-years-apart-from-family-203",
        "path": "/y-is-for-years-apart-from-family"
    },
    {
        "componentChunkName": "component---src-templates-single-js",
        "jsonName": "z-is-for-zimmerman-5de",
        "path": "/z-is-for-zimmerman"
    }
]